ntropy_sdk/__init__.py
ntropy_sdk/account_holders.py
ntropy_sdk/bank_statements.py
ntropy_sdk/batches.py
ntropy_sdk/categories.py
ntropy_sdk/entities.py
ntropy_sdk/http.py
ntropy_sdk/paging.py
ntropy_sdk/py.typed
ntropy_sdk/reports.py
ntropy_sdk/rules.py
ntropy_sdk/sdk.py
ntropy_sdk/transactions.py
ntropy_sdk/utils.py
ntropy_sdk/version.py
ntropy_sdk/webhooks.py
ntropy_sdk/async_/__init__.py
ntropy_sdk/async_/http.py
ntropy_sdk/async_/paging.py
ntropy_sdk/async_/sdk.py
ntropy_sdk/v2/__init__.py
ntropy_sdk/v2/bank_statements.py
ntropy_sdk/v2/errors.py
ntropy_sdk/v2/income_check.py
ntropy_sdk/v2/ntropy_sdk.py
ntropy_sdk/v2/recurring_payments.py
ntropy_sdk-5.3.0.dist-info/licenses/LICENSE
ntropy_sdk-5.3.0.dist-info/METADATA
ntropy_sdk-5.3.0.dist-info/WHEEL
ntropy_sdk-5.3.0.dist-info/entry_points.txt
ntropy_sdk-5.3.0.dist-info/top_level.txt
ntropy_sdk-5.3.0.dist-info/RECORD
