Metadata-Version: 2.4
Name: ntropy_sdk
Version: 5.3.0
Summary: SDK for the Ntropy API
Home-page: https://github.com/ntropy-network/ntropy-sdk
Author: Ntropy
Author-email: dev@ntropy.com
License: MIT license
Keywords: ntropy_sdk
Classifier: Development Status :: 2 - Pre-Alpha
Classifier: Intended Audience :: Developers
Classifier: License :: OSI Approved :: MIT License
Classifier: Natural Language :: English
Classifier: Programming Language :: Python :: 3
Classifier: Programming Language :: Python :: 3.8
Requires-Python: >=3.8
License-File: LICENSE
Requires-Dist: requests
Requires-Dist: tqdm
Requires-Dist: requests_toolbelt
Requires-Dist: pydantic
Requires-Dist: tabulate
Requires-Dist: aiohttp
Provides-Extra: models
Requires-Dist: pandas; extra == "models"
Requires-Dist: scikit-learn; extra == "models"
Requires-Dist: numpy; extra == "models"
Dynamic: author
Dynamic: author-email
Dynamic: classifier
Dynamic: description
Dynamic: description-content-type
Dynamic: home-page
Dynamic: keywords
Dynamic: license
Dynamic: license-file
Dynamic: provides-extra
Dynamic: requires-dist
Dynamic: requires-python
Dynamic: summary
